powerfuldeveloper/__init__.py
powerfuldeveloper/json_walker.py
tests/__init__.py
tests/test_json_walker.py
powerfuldeveloper_json_walker-0.0.6.dist-info/LICENSE
powerfuldeveloper_json_walker-0.0.6.dist-info/METADATA
powerfuldeveloper_json_walker-0.0.6.dist-info/WHEEL
powerfuldeveloper_json_walker-0.0.6.dist-info/top_level.txt
powerfuldeveloper_json_walker-0.0.6.dist-info/RECORD
