Metadata-Version: 2.2
Name: powerfuldeveloper-json-walker
Version: 0.0.6
Summary: Walk on jsons like nothing :)
Home-page: https://github.com/powerfuldeveloper/json_walker
Author: Powerfuldevleoper
Author-email: apowerfuldeveloper@gmail.com
Classifier: Programming Language :: Python :: 3
Classifier: License :: OSI Approved :: MIT License
Classifier: Operating System :: OS Independent
Requires-Python: >=3
License-File: LICENSE
Dynamic: author
Dynamic: author-email
Dynamic: classifier
Dynamic: description
Dynamic: description-content-type
Dynamic: home-page
Dynamic: requires-python
Dynamic: summary
